[
  {
    "ticker":"APD",
    "cash":1856000000.0,
    "ocf_current":3256800000.0,
    "burn_rate":1.7547413793,
    "runway_quarters":"N\/A - Positive OCF",
    "cash_flow_trend":"Recently Deteriorating",
    "Security":"Air Products",
    "GICS Sector":"Materials"
  },
  {
    "ticker":"ALB",
    "cash":1618001000.0,
    "ocf_current":1282267000.0,
    "burn_rate":0.7925007463,
    "runway_quarters":"N\/A - Positive OCF",
    "cash_flow_trend":"Recently Improving",
    "Security":"Albemarle Corporation",
    "GICS Sector":"Materials"
  },
  {
    "ticker":"ARE",
    "cash":549062000.0,
    "ocf_current":1414046000.0,
    "burn_rate":2.5753849292,
    "runway_quarters":"N\/A - Positive OCF",
    "cash_flow_trend":"Consistently Deteriorating",
    "Security":"Alexandria Real Estate Equities",
    "GICS Sector":"Real Estate"
  },
  {
    "ticker":"BAX",
    "cash":1966000000.0,
    "ocf_current":845000000.0,
    "burn_rate":0.4298067141,
    "runway_quarters":"N\/A - Positive OCF",
    "cash_flow_trend":"Consistently Deteriorating",
    "Security":"Baxter International",
    "GICS Sector":"Health Care"
  },
  {
    "ticker":"CNC",
    "cash":17888000000.0,
    "ocf_current":5088000000.0,
    "burn_rate":0.2844364937,
    "runway_quarters":"N\/A - Positive OCF",
    "cash_flow_trend":"Recently Improving",
    "Security":"Centene Corporation",
    "GICS Sector":"Health Care"
  },
  {
    "ticker":"CRL",
    "cash":213770000.0,
    "ocf_current":737646000.0,
    "burn_rate":3.4506525705,
    "runway_quarters":"N\/A - Positive OCF",
    "cash_flow_trend":"Consistently Improving",
    "Security":"Charles River Laboratories",
    "GICS Sector":"Health Care"
  },
  {
    "ticker":"CRWD",
    "cash":5230125000.0,
    "ocf_current":1612349000.0,
    "burn_rate":0.3082811596,
    "runway_quarters":"N\/A - Positive OCF",
    "cash_flow_trend":"Consistently Improving",
    "Security":"CrowdStrike",
    "GICS Sector":"Information Technology"
  },
  {
    "ticker":"DOW",
    "cash":3816000000.0,
    "ocf_current":1032000000.0,
    "burn_rate":0.2704402516,
    "runway_quarters":"N\/A - Positive OCF",
    "cash_flow_trend":"Consistently Deteriorating",
    "Security":"Dow Inc.",
    "GICS Sector":"Materials"
  },
  {
    "ticker":"DD",
    "cash":715000000.0,
    "ocf_current":560000000.0,
    "burn_rate":0.7832167832,
    "runway_quarters":"N\/A - Positive OCF",
    "cash_flow_trend":"Consistently Deteriorating",
    "Security":"DuPont",
    "GICS Sector":"Materials"
  },
  {
    "ticker":"ECHO",
    "cash":1883074000.0,
    "ocf_current":-99374000.0,
    "burn_rate":-0.0527722224,
    "runway_quarters":75.7974520498,
    "cash_flow_trend":"Consistently Deteriorating",
    "Security":"EchoStar",
    "GICS Sector":"Communication Services"
  },
  {
    "ticker":"EL",
    "cash":2921000000.0,
    "ocf_current":1272000000.0,
    "burn_rate":0.4354673057,
    "runway_quarters":"N\/A - Positive OCF",
    "cash_flow_trend":"Consistently Deteriorating",
    "Security":"Est\u00e9e Lauder Companies (The)",
    "GICS Sector":"Consumer Staples"
  },
  {
    "ticker":"F",
    "cash":23356000000.0,
    "ocf_current":21282000000.0,
    "burn_rate":0.911200548,
    "runway_quarters":"N\/A - Positive OCF",
    "cash_flow_trend":"Consistently Improving",
    "Security":"Ford Motor Company",
    "GICS Sector":"Consumer Discretionary"
  },
  {
    "ticker":"HAS",
    "cash":776200000.0,
    "ocf_current":893200000.0,
    "burn_rate":1.1507343468,
    "runway_quarters":"N\/A - Positive OCF",
    "cash_flow_trend":"Consistently Improving",
    "Security":"Hasbro",
    "GICS Sector":"Consumer Discretionary"
  },
  {
    "ticker":"INTC",
    "cash":14265000000.0,
    "ocf_current":9697000000.0,
    "burn_rate":0.6797756747,
    "runway_quarters":"N\/A - Positive OCF",
    "cash_flow_trend":"Recently Improving",
    "Security":"Intel",
    "GICS Sector":"Information Technology"
  },
  {
    "ticker":"IFF",
    "cash":590000000.0,
    "ocf_current":850000000.0,
    "burn_rate":1.4406779661,
    "runway_quarters":"N\/A - Positive OCF",
    "cash_flow_trend":"Consistently Deteriorating",
    "Security":"International Flavors & Fragrances",
    "GICS Sector":"Materials"
  },
  {
    "ticker":"IP",
    "cash":1145000000.0,
    "ocf_current":1698000000.0,
    "burn_rate":1.4829694323,
    "runway_quarters":"N\/A - Positive OCF",
    "cash_flow_trend":"Recently Improving",
    "Security":"International Paper",
    "GICS Sector":"Materials"
  },
  {
    "ticker":"IVZ",
    "cash":1979800000.0,
    "ocf_current":1525300000.0,
    "burn_rate":0.7704313567,
    "runway_quarters":"N\/A - Positive OCF",
    "cash_flow_trend":"Consistently Improving",
    "Security":"Invesco",
    "GICS Sector":"Financials"
  },
  {
    "ticker":"KHC",
    "cash":2615000000.0,
    "ocf_current":4462000000.0,
    "burn_rate":1.7063097514,
    "runway_quarters":"N\/A - Positive OCF",
    "cash_flow_trend":"Consistently Improving",
    "Security":"Kraft Heinz",
    "GICS Sector":"Consumer Staples"
  },
  {
    "ticker":"LYB",
    "cash":3443000000.0,
    "ocf_current":2262000000.0,
    "burn_rate":0.6569851873,
    "runway_quarters":"N\/A - Positive OCF",
    "cash_flow_trend":"Consistently Deteriorating",
    "Security":"LyondellBasell",
    "GICS Sector":"Materials"
  },
  {
    "ticker":"MRNA",
    "cash":2595000000.0,
    "ocf_current":-1873000000.0,
    "burn_rate":-0.7217726397,
    "runway_quarters":5.5419113721,
    "cash_flow_trend":"Consistently Improving",
    "Security":"Moderna",
    "GICS Sector":"Health Care"
  },
  {
    "ticker":"TAP",
    "cash":896500000.0,
    "ocf_current":1784400000.0,
    "burn_rate":1.9904071389,
    "runway_quarters":"N\/A - Positive OCF",
    "cash_flow_trend":"Consistently Deteriorating",
    "Security":"Molson Coors Beverage Company",
    "GICS Sector":"Consumer Staples"
  },
  {
    "ticker":"OMC",
    "cash":6881100000.0,
    "ocf_current":2938200000.0,
    "burn_rate":0.4269956838,
    "runway_quarters":"N\/A - Positive OCF",
    "cash_flow_trend":"Consistently Improving",
    "Security":"Omnicom Group",
    "GICS Sector":"Communication Services"
  },
  {
    "ticker":"PSKY",
    "cash":3274000000.0,
    "ocf_current":752000000.0,
    "burn_rate":0.2296884545,
    "runway_quarters":"N\/A - Positive OCF",
    "cash_flow_trend":"Consistently Improving",
    "Security":"Paramount Skydance Corporation",
    "GICS Sector":"Communication Services"
  },
  {
    "ticker":"SNDK",
    "cash":1481000000.0,
    "ocf_current":84000000.0,
    "burn_rate":0.0567184335,
    "runway_quarters":"N\/A - Positive OCF",
    "cash_flow_trend":"Consistently Improving",
    "Security":"Sandisk",
    "GICS Sector":"Information Technology"
  },
  {
    "ticker":"SJM",
    "cash":58600000.0,
    "ocf_current":1473600000.0,
    "burn_rate":25.1467576792,
    "runway_quarters":"N\/A - Positive OCF",
    "cash_flow_trend":"Consistently Improving",
    "Security":"J.M. Smucker Company (The)",
    "GICS Sector":"Consumer Staples"
  },
  {
    "ticker":"TTWO",
    "cash":1545500000.0,
    "ocf_current":624300000.0,
    "burn_rate":0.4039469427,
    "runway_quarters":"N\/A - Positive OCF",
    "cash_flow_trend":"Consistently Improving",
    "Security":"Take-Two Interactive",
    "GICS Sector":"Communication Services"
  },
  {
    "ticker":"VTRS",
    "cash":1322400000.0,
    "ocf_current":2315900000.0,
    "burn_rate":1.7512855414,
    "runway_quarters":"N\/A - Positive OCF",
    "cash_flow_trend":"Recently Improving",
    "Security":"Viatris",
    "GICS Sector":"Health Care"
  }
]